icostate/__init__.py
icostate/config.py
icostate/error.py
icostate/sensor.py
icostate/state.py
icostate/system.py
icostate-0.22.0.dist-info/METADATA
icostate-0.22.0.dist-info/WHEEL
icostate-0.22.0.dist-info/RECORD
