Metadata-Version: 2.4
Name: icostate
Version: 0.22.0
Summary: Stateful API for the ICOtronic system intended for usage in a Web API
Keywords: smart-tool,smh,stu,sth,tool-holder
Author: Moritz Breurather
Author-email: breurather@ift.at
Requires-Python: >=3.12,<4
Classifier: Programming Language :: Python :: 3
Classifier: Programming Language :: Python :: 3.12
Classifier: Programming Language :: Python :: 3.13
Classifier: Programming Language :: Python :: 3.14
Provides-Extra: dev
Provides-Extra: test
Requires-Dist: Flake8-pyproject (>=1.2.3) ; extra == "dev"
Requires-Dist: anyio (>=4.11) ; extra == "test"
Requires-Dist: black (>=25.1.0) ; extra == "dev"
Requires-Dist: coverage (>=7.9.2) ; extra == "dev"
Requires-Dist: dynaconf (>=3.1.12,<4)
Requires-Dist: icotronic (>=6.0.1,<7)
Requires-Dist: mypy (>=1.16.1) ; extra == "dev"
Requires-Dist: myst-parser (>=4.0.1) ; extra == "dev"
Requires-Dist: netaddr (>=1.3.0)
Requires-Dist: pydoclint[flake8] (>=0.6.6) ; extra == "dev"
Requires-Dist: pyee (>=13.0.0)
Requires-Dist: pylint (>=3.3.7) ; extra == "dev"
Requires-Dist: pytest (>=9.0) ; extra == "dev"
Requires-Dist: pytest-rerunfailures (>=16.1) ; extra == "test"
Requires-Dist: pytest-sphinx (>=0.6.3) ; extra == "test"
Requires-Dist: pytest-sugar (>=1.1.1) ; extra == "test"
Requires-Dist: sphinx-autodoc-typehints (>=3) ; extra == "dev"
Requires-Dist: sphinx-pyproject (>=0.3) ; extra == "dev"
Requires-Dist: sphinx_rtd_theme ; extra == "dev"
Requires-Dist: sphinx_toggleprompt (>=0.6.0) ; extra == "dev"
Requires-Dist: sphinxcontrib-mermaid (>=1.0.0) ; extra == "dev"
Project-URL: Documentation, https://icostate.readthedocs.io
Project-URL: Source, https://github.com/mytoolit/ICOstate
